invenio_shibboleth/__init__.py
invenio_shibboleth/config.py
invenio_shibboleth/ext.py
invenio_shibboleth/handlers.py
invenio_shibboleth/invenio_app.py
invenio_shibboleth/version.py
invenio_shibboleth/flask_sso_saml/__init__.py
invenio_shibboleth/flask_sso_saml/_compat.py
invenio_shibboleth/flask_sso_saml/config.py
invenio_shibboleth/flask_sso_saml/ext.py
invenio_shibboleth/flask_sso_saml/proxies.py
invenio_shibboleth/flask_sso_saml/utils.py
invenio_shibboleth/flask_sso_saml/views.py
invenio_shibboleth/invenio_accounts/__init__.py
invenio_shibboleth/invenio_accounts/errors.py
invenio_shibboleth/invenio_accounts/models.py
invenio_shibboleth/invenio_accounts/utils.py
invenio_shibboleth/translations/messages.pot
invenio_shibboleth/translations/de/LC_MESSAGES/messages.mo
invenio_shibboleth/translations/de/LC_MESSAGES/messages.po
invenio_shibboleth-1.0.4.dist-info/AUTHORS.rst
invenio_shibboleth-1.0.4.dist-info/LICENSE
invenio_shibboleth-1.0.4.dist-info/METADATA
invenio_shibboleth-1.0.4.dist-info/WHEEL
invenio_shibboleth-1.0.4.dist-info/entry_points.txt
invenio_shibboleth-1.0.4.dist-info/top_level.txt
invenio_shibboleth-1.0.4.dist-info/RECORD
