Metadata-Version: 2.1
Name: invenio-shibboleth
Version: 1.0.4
Summary: Invenio module module that provides SAML integration.
Home-page: https://github.com/tu-graz-library/invenio-shibboleth
Author: Mojib Wali
Author-email: mb_wali@hotmail.com
License: MIT
Keywords: invenio TODO
Platform: any
Classifier: Environment :: Web Environment
Classifier: Intended Audience :: Developers
Classifier: License :: OSI Approved :: MIT License
Classifier: Operating System :: OS Independent
Classifier: Programming Language :: Python
Classifier: Topic :: Internet :: WWW/HTTP :: Dynamic Content
Classifier: Topic :: Software Development :: Libraries :: Python Modules
Classifier: Programming Language :: Python :: 3
Classifier: Programming Language :: Python :: 3.6
Classifier: Programming Language :: Python :: 3.7
Classifier: Programming Language :: Python :: 3.8
Classifier: Development Status :: 3 - Alpha
Requires-Dist: python3-saml (>=1.5.0)
Requires-Dist: invenio-oauthclient (>=1.4.1)
Requires-Dist: invenio-accounts (>=1.4.0)
Requires-Dist: idna (<3,>=2.5)
Provides-Extra: all
Requires-Dist: Sphinx (>=3) ; extra == 'all'
Requires-Dist: pytest-invenio (>=1.4.1) ; extra == 'all'
Requires-Dist: invenio-app (<2.0.0,>=1.3.0) ; extra == 'all'
Requires-Dist: invenio-mail (>=1.0.0) ; extra == 'all'
Requires-Dist: invenio-userprofiles (>=1.0.0) ; extra == 'all'
Requires-Dist: redis (>=2.10.5) ; extra == 'all'
Requires-Dist: mock (>=2.0.0) ; extra == 'all'
Requires-Dist: psycopg2-binary (>=2.8.6) ; extra == 'all'
Provides-Extra: docs
Requires-Dist: Sphinx (>=3) ; extra == 'docs'
Provides-Extra: mysql
Requires-Dist: invenio-db[mysql,versioning] (<1.1.0,>=1.0.9) ; extra == 'mysql'
Provides-Extra: postgresql
Requires-Dist: invenio-db[postgresql,versioning] (<1.1.0,>=1.0.9) ; extra == 'postgresql'
Provides-Extra: sqlite
Requires-Dist: invenio-db[versioning] (<1.1.0,>=1.0.9) ; extra == 'sqlite'
Provides-Extra: tests
Requires-Dist: pytest-invenio (>=1.4.1) ; extra == 'tests'
Requires-Dist: invenio-app (<2.0.0,>=1.3.0) ; extra == 'tests'
Requires-Dist: invenio-mail (>=1.0.0) ; extra == 'tests'
Requires-Dist: invenio-userprofiles (>=1.0.0) ; extra == 'tests'
Requires-Dist: redis (>=2.10.5) ; extra == 'tests'
Requires-Dist: mock (>=2.0.0) ; extra == 'tests'
Requires-Dist: psycopg2-binary (>=2.8.6) ; extra == 'tests'
